__init__.py
delayviewer/__init__.py
delayviewer/delayviewer_cli.py
delayviewer/spinner.py
delayviewer/stopwatch.py
delayviewer/time_and_delay.py
delayviewer-0.1.1.dist-info/LICENSE
delayviewer-0.1.1.dist-info/METADATA
delayviewer-0.1.1.dist-info/WHEEL
delayviewer-0.1.1.dist-info/entry_points.txt
delayviewer-0.1.1.dist-info/top_level.txt
delayviewer-0.1.1.dist-info/RECORD
