Metadata-Version: 2.1
Name: delayviewer
Version: 0.1.1
Summary: Several mechanisms to time and view progress of execution/runtime delays in Python
Author-email: Ed Waldner <waldevburry@proton.me>
Maintainer-email: Ed Waldner <waldevburry@proton.me>
Project-URL: Homepage, https://github.com/ew98/delayviewer
Project-URL: Documentation, https://github.com/ew98/delayviewer/wiki/DelayViewer
Project-URL: Issues, https://github.com/ew98/delayviewer/issues
Keywords: util,utility
Classifier: Development Status :: 3 - Alpha
Classifier: Environment :: Console
Classifier: Intended Audience :: Developers
Classifier: License :: OSI Approved :: MIT License
Classifier: Natural Language :: English
Classifier: Programming Language :: Python :: 3.9
Classifier: Programming Language :: Python :: 3.10
Classifier: Programming Language :: Python :: 3.11
Classifier: Operating System :: OS Independent
Classifier: Topic :: Utilities
Requires-Python: >=3.9
License-File: LICENSE
Requires-Dist: argcomplete
Requires-Dist: quickcolor
Requires-Dist: showexception
